{
  "label": "V",
  "image_path": "C:\\Users\\Andrii\\Documents\\GitHub\\Hybrid-handwriting-recognition\\data\\raw\\images\\upper_V\\upper_V_20260525_112127_474112.png",
  "canvas_width": 400,
  "canvas_height": 400,
  "strokes": [
    {
      "x": 54.80126953125,
      "y": 86.08273315429688,
      "t": 0.0,
      "pressure": 0.5,
      "pen_down": true
    },
    {
      "x": 56.9185791015625,
      "y": 89.89376831054688,
      "t": 0.8999999761581421,
      "pressure": 0.5,
      "pen_down": true
    },
    {
      "x": 66.6578369140625,
      "y": 111.9130859375,
      "t": 13.100000023841858,
      "pressure": 0.5,
      "pen_down": true
    },
    {
      "x": 81.478515625,
      "y": 144.51858520507812,
      "t": 32.0,
      "pressure": 0.5,
      "pen_down": true
    },
    {
      "x": 94.60546875,
      "y": 176.27719116210938,
      "t": 48.89999997615814,
      "pressure": 0.5,
      "pen_down": true
    },
    {
      "x": 109.4261474609375,
      "y": 210.15304565429688,
      "t": 69.0,
      "pressure": 0.5,
      "pen_down": true
    },
    {
      "x": 119.5888671875,
      "y": 243.60546875,
      "t": 82.10000002384186,
      "pressure": 0.5,
      "pen_down": true
    },
    {
      "x": 125.5172119140625,
      "y": 271.1296081542969,
      "t": 99.89999997615814,
      "pressure": 0.5,
      "pen_down": true
    },
    {
      "x": 129.3282470703125,
      "y": 291.0316467285156,
      "t": 115.10000002384186,
      "pressure": 0.5,
      "pen_down": true
    },
    {
      "x": 131.4454345703125,
      "y": 302.04132080078125,
      "t": 131.79999995231628,
      "pressure": 0.5,
      "pen_down": true
    },
    {
      "x": 133.1392822265625,
      "y": 303.735107421875,
      "t": 148.39999997615814,
      "pressure": 0.5,
      "pen_down": true
    },
    {
      "x": 133.1392822265625,
      "y": 294.41925048828125,
      "t": 165.0,
      "pressure": 0.5,
      "pen_down": true
    },
    {
      "x": 133.562744140625,
      "y": 266.8951110839844,
      "t": 182.10000002384186,
      "pressure": 0.5,
      "pen_down": true
    },
    {
      "x": 133.986083984375,
      "y": 229.63168334960938,
      "t": 198.39999997615814,
      "pressure": 0.5,
      "pen_down": true
    },
    {
      "x": 134.8330078125,
      "y": 188.98065185546875,
      "t": 214.89999997615814,
      "pressure": 0.5,
      "pen_down": true
    },
    {
      "x": 140.7613525390625,
      "y": 146.63580322265625,
      "t": 232.29999995231628,
      "pressure": 0.5,
      "pen_down": true
    },
    {
      "x": 151.3475341796875,
      "y": 108.10205078125,
      "t": 249.39999997615814,
      "pressure": 0.5,
      "pen_down": true
    },
    {
      "x": 161.9337158203125,
      "y": 79.30755615234375,
      "t": 264.89999997615814,
      "pressure": 0.5,
      "pen_down": true
    },
    {
      "x": 172.5198974609375,
      "y": 58.13514709472656,
      "t": 281.7000000476837,
      "pressure": 0.5,
      "pen_down": true
    },
    {
      "x": 172.5198974609375,
      "y": 58.13514709472656,
      "t": 286.2999999523163,
      "pressure": 0.5,
      "pen_down": false
    }
  ]
}