{
  "label": "D",
  "image_path": "C:\\Users\\Andrii\\Documents\\GitHub\\Hybrid-handwriting-recognition\\data\\raw\\images\\upper_D\\upper_D_20260525_102011_797759.png",
  "canvas_width": 400,
  "canvas_height": 400,
  "strokes": [
    {
      "x": 160.4605712890625,
      "y": 138.04962158203125,
      "t": 0.0,
      "pressure": 0.5,
      "pen_down": true
    },
    {
      "x": 160.037109375,
      "y": 138.89651489257812,
      "t": 1.2000000476837158,
      "pressure": 0.5,
      "pen_down": true
    },
    {
      "x": 157.072998046875,
      "y": 153.71719360351562,
      "t": 14.0,
      "pressure": 0.5,
      "pen_down": true
    },
    {
      "x": 151.5682373046875,
      "y": 185.0523681640625,
      "t": 37.90000009536743,
      "pressure": 0.5,
      "pen_down": true
    },
    {
      "x": 146.9102783203125,
      "y": 213.84683227539062,
      "t": 59.40000009536743,
      "pressure": 0.5,
      "pen_down": true
    },
    {
      "x": 143.0992431640625,
      "y": 251.95718383789062,
      "t": 82.30000007152557,
      "pressure": 0.5,
      "pen_down": true
    },
    {
      "x": 142.2523193359375,
      "y": 264.66064453125,
      "t": 98.40000009536743,
      "pressure": 0.5,
      "pen_down": true
    },
    {
      "x": 142.2523193359375,
      "y": 268.0482177734375,
      "t": 116.30000007152557,
      "pressure": 0.5,
      "pen_down": true
    },
    {
      "x": 142.2523193359375,
      "y": 268.0482177734375,
      "t": 119.10000002384186,
      "pressure": 0.5,
      "pen_down": false
    },
    {
      "x": 142.2523193359375,
      "y": 179.97097778320312,
      "t": 252.40000009536743,
      "pressure": 0.5,
      "pen_down": true
    },
    {
      "x": 144.36962890625,
      "y": 176.58340454101562,
      "t": 253.0,
      "pressure": 0.5,
      "pen_down": true
    },
    {
      "x": 154.10888671875,
      "y": 163.03305053710938,
      "t": 264.60000002384186,
      "pressure": 0.5,
      "pen_down": true
    },
    {
      "x": 170.199951171875,
      "y": 151.176513671875,
      "t": 284.40000009536743,
      "pressure": 0.5,
      "pen_down": true
    },
    {
      "x": 187.1378173828125,
      "y": 145.67169189453125,
      "t": 304.5,
      "pressure": 0.5,
      "pen_down": true
    },
    {
      "x": 204.499267578125,
      "y": 144.82476806640625,
      "t": 322.0,
      "pressure": 0.5,
      "pen_down": true
    },
    {
      "x": 220.166748046875,
      "y": 150.32962036132812,
      "t": 338.5,
      "pressure": 0.5,
      "pen_down": true
    },
    {
      "x": 232.44677734375,
      "y": 162.609619140625,
      "t": 354.60000002384186,
      "pressure": 0.5,
      "pen_down": true
    },
    {
      "x": 237.95166015625,
      "y": 177.0068359375,
      "t": 371.2000000476837,
      "pressure": 0.5,
      "pen_down": true
    },
    {
      "x": 237.5281982421875,
      "y": 193.09786987304688,
      "t": 388.0,
      "pressure": 0.5,
      "pen_down": true
    },
    {
      "x": 229.482666015625,
      "y": 217.23443603515625,
      "t": 404.5,
      "pressure": 0.5,
      "pen_down": true
    },
    {
      "x": 214.6619873046875,
      "y": 241.79443359375,
      "t": 421.2000000476837,
      "pressure": 0.5,
      "pen_down": true
    },
    {
      "x": 197.300537109375,
      "y": 259.5792541503906,
      "t": 437.90000009536743,
      "pressure": 0.5,
      "pen_down": true
    },
    {
      "x": 177.3985595703125,
      "y": 273.55303955078125,
      "t": 454.40000009536743,
      "pressure": 0.5,
      "pen_down": true
    },
    {
      "x": 162.577880859375,
      "y": 279.9047546386719,
      "t": 471.10000002384186,
      "pressure": 0.5,
      "pen_down": true
    },
    {
      "x": 158.3433837890625,
      "y": 281.17510986328125,
      "t": 486.40000009536743,
      "pressure": 0.5,
      "pen_down": true
    },
    {
      "x": 158.3433837890625,
      "y": 281.17510986328125,
      "t": 488.3000000715256,
      "pressure": 0.5,
      "pen_down": false
    }
  ]
}