{
  "label": "W",
  "image_path": "C:\\Users\\Andrii\\Documents\\GitHub\\Hybrid-handwriting-recognition\\data\\raw\\images\\upper_W\\upper_W_20260525_112332_372218.png",
  "canvas_width": 400,
  "canvas_height": 400,
  "strokes": [
    {
      "x": 169.13232421875,
      "y": 95.39859008789062,
      "t": 0.0,
      "pressure": 0.5,
      "pen_down": true
    },
    {
      "x": 171.673095703125,
      "y": 128.85101318359375,
      "t": 0.7000000476837158,
      "pressure": 0.5,
      "pen_down": true
    },
    {
      "x": 178.87158203125,
      "y": 173.73651123046875,
      "t": 34.200000047683716,
      "pressure": 0.5,
      "pen_down": true
    },
    {
      "x": 181.412353515625,
      "y": 190.2509765625,
      "t": 54.300000071525574,
      "pressure": 0.5,
      "pen_down": true
    },
    {
      "x": 183.106201171875,
      "y": 204.22479248046875,
      "t": 68.60000002384186,
      "pressure": 0.5,
      "pen_down": true
    },
    {
      "x": 183.9530029296875,
      "y": 216.08132934570312,
      "t": 85.0,
      "pressure": 0.5,
      "pen_down": true
    },
    {
      "x": 184.7999267578125,
      "y": 222.00961303710938,
      "t": 101.89999997615814,
      "pressure": 0.5,
      "pen_down": true
    },
    {
      "x": 186.917236328125,
      "y": 222.00961303710938,
      "t": 119.30000007152557,
      "pressure": 0.5,
      "pen_down": true
    },
    {
      "x": 190.728271484375,
      "y": 212.69375610351562,
      "t": 134.89999997615814,
      "pressure": 0.5,
      "pen_down": true
    },
    {
      "x": 198.350341796875,
      "y": 194.90890502929688,
      "t": 152.30000007152557,
      "pressure": 0.5,
      "pen_down": true
    },
    {
      "x": 208.089599609375,
      "y": 174.58340454101562,
      "t": 167.80000007152557,
      "pressure": 0.5,
      "pen_down": true
    },
    {
      "x": 219.0992431640625,
      "y": 151.71719360351562,
      "t": 184.30000007152557,
      "pressure": 0.5,
      "pen_down": true
    },
    {
      "x": 230.955810546875,
      "y": 132.66204833984375,
      "t": 203.0,
      "pressure": 0.5,
      "pen_down": true
    },
    {
      "x": 243.6591796875,
      "y": 118.2647705078125,
      "t": 219.0,
      "pressure": 0.5,
      "pen_down": true
    },
    {
      "x": 253.3985595703125,
      "y": 111.066162109375,
      "t": 234.80000007152557,
      "pressure": 0.5,
      "pen_down": true
    },
    {
      "x": 261.867431640625,
      "y": 109.37237548828125,
      "t": 252.0,
      "pressure": 0.5,
      "pen_down": true
    },
    {
      "x": 267.372314453125,
      "y": 113.60687255859375,
      "t": 268.0,
      "pressure": 0.5,
      "pen_down": true
    },
    {
      "x": 272.0302734375,
      "y": 127.1572265625,
      "t": 284.60000002384186,
      "pressure": 0.5,
      "pen_down": true
    },
    {
      "x": 272.0302734375,
      "y": 150.02340698242188,
      "t": 301.39999997615814,
      "pressure": 0.5,
      "pen_down": true
    },
    {
      "x": 267.7957763671875,
      "y": 175.853759765625,
      "t": 318.5,
      "pressure": 0.5,
      "pen_down": true
    },
    {
      "x": 261.867431640625,
      "y": 197.02615356445312,
      "t": 334.60000002384186,
      "pressure": 0.5,
      "pen_down": true
    },
    {
      "x": 256.3626708984375,
      "y": 215.23443603515625,
      "t": 352.0,
      "pressure": 0.5,
      "pen_down": true
    },
    {
      "x": 253.3985595703125,
      "y": 226.24407958984375,
      "t": 368.10000002384186,
      "pressure": 0.5,
      "pen_down": true
    },
    {
      "x": 253.3985595703125,
      "y": 231.32546997070312,
      "t": 384.60000002384186,
      "pressure": 0.5,
      "pen_down": true
    },
    {
      "x": 256.7861328125,
      "y": 227.51443481445312,
      "t": 401.3000000715256,
      "pressure": 0.5,
      "pen_down": true
    },
    {
      "x": 268.6427001953125,
      "y": 209.30615234375,
      "t": 418.10000002384186,
      "pressure": 0.5,
      "pen_down": true
    },
    {
      "x": 287.2744140625,
      "y": 180.93511962890625,
      "t": 435.5,
      "pressure": 0.5,
      "pen_down": true
    },
    {
      "x": 306.32958984375,
      "y": 149.5999755859375,
      "t": 453.2000000476837,
      "pressure": 0.5,
      "pen_down": true
    },
    {
      "x": 325.80810546875,
      "y": 116.99444580078125,
      "t": 467.8000000715256,
      "pressure": 0.5,
      "pen_down": true
    },
    {
      "x": 344.43994140625,
      "y": 88.6234130859375,
      "t": 484.5,
      "pressure": 0.5,
      "pen_down": true
    },
    {
      "x": 362.648193359375,
      "y": 61.94618225097656,
      "t": 501.3000000715256,
      "pressure": 0.5,
      "pen_down": true
    },
    {
      "x": 376.6219482421875,
      "y": 43.314453125,
      "t": 517.5,
      "pressure": 0.5,
      "pen_down": true
    },
    {
      "x": 376.6219482421875,
      "y": 43.314453125,
      "t": 523.0,
      "pressure": 0.5,
      "pen_down": false
    }
  ]
}