{
  "label": "x",
  "image_path": "C:\\Users\\Andrii\\Documents\\GitHub\\Hybrid-handwriting-recognition\\data\\raw\\images\\lower_x\\lower_x_20260525_112729_671217.png",
  "canvas_width": 400,
  "canvas_height": 400,
  "strokes": [
    {
      "x": 215.0037841796875,
      "y": 129.2103271484375,
      "t": 0.0,
      "pressure": 0.5,
      "pen_down": true
    },
    {
      "x": 209.438232421875,
      "y": 136.4884033203125,
      "t": 0.3999999761581421,
      "pressure": 0.5,
      "pen_down": true
    },
    {
      "x": 187.60400390625,
      "y": 162.17562866210938,
      "t": 20.299999952316284,
      "pressure": 0.5,
      "pen_down": true
    },
    {
      "x": 164.057373046875,
      "y": 189.57534790039062,
      "t": 30.299999952316284,
      "pressure": 0.5,
      "pen_down": true
    },
    {
      "x": 146.5045166015625,
      "y": 207.556396484375,
      "t": 48.799999952316284,
      "pressure": 0.5,
      "pen_down": true
    },
    {
      "x": 146.5045166015625,
      "y": 207.556396484375,
      "t": 52.5,
      "pressure": 0.5,
      "pen_down": false
    },
    {
      "x": 154.210693359375,
      "y": 137.34463500976562,
      "t": 215.5,
      "pressure": 0.5,
      "pen_down": true
    },
    {
      "x": 157.20751953125,
      "y": 139.05712890625,
      "t": 230.79999995231628,
      "pressure": 0.5,
      "pen_down": true
    },
    {
      "x": 166.197998046875,
      "y": 146.33517456054688,
      "t": 248.5,
      "pressure": 0.5,
      "pen_down": true
    },
    {
      "x": 179.0416259765625,
      "y": 158.75067138671875,
      "t": 263.89999997615814,
      "pressure": 0.5,
      "pen_down": true
    },
    {
      "x": 191.88525390625,
      "y": 171.59429931640625,
      "t": 281.0,
      "pressure": 0.5,
      "pen_down": true
    },
    {
      "x": 204.7288818359375,
      "y": 185.72225952148438,
      "t": 297.6999999284744,
      "pressure": 0.5,
      "pen_down": true
    },
    {
      "x": 208.15380859375,
      "y": 189.147216796875,
      "t": 311.2999999523163,
      "pressure": 0.5,
      "pen_down": true
    },
    {
      "x": 208.15380859375,
      "y": 189.147216796875,
      "t": 311.6999999284744,
      "pressure": 0.5,
      "pen_down": false
    }
  ]
}