{
  "label": "P",
  "image_path": "C:\\Users\\Andrii\\Documents\\GitHub\\Hybrid-handwriting-recognition\\data\\raw\\images\\upper_P\\upper_P_20260525_110826_574452.png",
  "canvas_width": 400,
  "canvas_height": 400,
  "strokes": [
    {
      "x": 229.261962890625,
      "y": 37.80963134765625,
      "t": 0.0,
      "pressure": 0.5,
      "pen_down": true
    },
    {
      "x": 229.261962890625,
      "y": 38.656524658203125,
      "t": 0.6999999284744263,
      "pressure": 0.5,
      "pen_down": true
    },
    {
      "x": 227.144775390625,
      "y": 51.35997009277344,
      "t": 13.299999952316284,
      "pressure": 0.5,
      "pen_down": true
    },
    {
      "x": 221.2164306640625,
      "y": 83.54203796386719,
      "t": 38.299999952316284,
      "pressure": 0.5,
      "pen_down": true
    },
    {
      "x": 213.1708984375,
      "y": 121.22894287109375,
      "t": 53.39999997615814,
      "pressure": 0.5,
      "pen_down": true
    },
    {
      "x": 204.7020263671875,
      "y": 161.45651245117188,
      "t": 68.29999995231628,
      "pressure": 0.5,
      "pen_down": true
    },
    {
      "x": 197.0799560546875,
      "y": 197.02615356445312,
      "t": 85.10000002384186,
      "pressure": 0.5,
      "pen_down": true
    },
    {
      "x": 189.88134765625,
      "y": 231.7489013671875,
      "t": 101.5,
      "pressure": 0.5,
      "pen_down": true
    },
    {
      "x": 184.7999267578125,
      "y": 260.54339599609375,
      "t": 118.10000002384186,
      "pressure": 0.5,
      "pen_down": true
    },
    {
      "x": 182.25927734375,
      "y": 284.2565002441406,
      "t": 134.79999995231628,
      "pressure": 0.5,
      "pen_down": true
    },
    {
      "x": 181.8358154296875,
      "y": 299.0771789550781,
      "t": 151.60000002384186,
      "pressure": 0.5,
      "pen_down": true
    },
    {
      "x": 182.25927734375,
      "y": 304.5820007324219,
      "t": 171.39999997615814,
      "pressure": 0.5,
      "pen_down": true
    },
    {
      "x": 182.25927734375,
      "y": 304.5820007324219,
      "t": 180.39999997615814,
      "pressure": 0.5,
      "pen_down": false
    },
    {
      "x": 213.1708984375,
      "y": 75.07307434082031,
      "t": 330.7999999523163,
      "pressure": 0.5,
      "pen_down": true
    },
    {
      "x": 214.86474609375,
      "y": 72.53237915039062,
      "t": 331.39999997615814,
      "pressure": 0.5,
      "pen_down": true
    },
    {
      "x": 223.333740234375,
      "y": 64.48686218261719,
      "t": 346.6999999284744,
      "pressure": 0.5,
      "pen_down": true
    },
    {
      "x": 239.4248046875,
      "y": 57.711700439453125,
      "t": 363.1999999284744,
      "pressure": 0.5,
      "pen_down": true
    },
    {
      "x": 258.47998046875,
      "y": 56.86480712890625,
      "t": 380.0,
      "pressure": 0.5,
      "pen_down": true
    },
    {
      "x": 281.76953125,
      "y": 61.09928894042969,
      "t": 398.5,
      "pressure": 0.5,
      "pen_down": true
    },
    {
      "x": 315.221923828125,
      "y": 85.23582458496094,
      "t": 435.10000002384186,
      "pressure": 0.5,
      "pen_down": true
    },
    {
      "x": 317.3392333984375,
      "y": 100.0565185546875,
      "t": 454.2999999523163,
      "pressure": 0.5,
      "pen_down": true
    },
    {
      "x": 306.32958984375,
      "y": 119.95858764648438,
      "t": 468.10000002384186,
      "pressure": 0.5,
      "pen_down": true
    },
    {
      "x": 280.499267578125,
      "y": 143.24822998046875,
      "t": 485.7999999523163,
      "pressure": 0.5,
      "pen_down": true
    },
    {
      "x": 250.85791015625,
      "y": 163.15029907226562,
      "t": 501.5,
      "pressure": 0.5,
      "pen_down": true
    },
    {
      "x": 243.23583984375,
      "y": 168.231689453125,
      "t": 517.0,
      "pressure": 0.5,
      "pen_down": true
    },
    {
      "x": 243.23583984375,
      "y": 168.231689453125,
      "t": 518.1999999284744,
      "pressure": 0.5,
      "pen_down": false
    }
  ]
}