{
  "label": "P",
  "image_path": "C:\\Users\\Andrii\\Documents\\GitHub\\Hybrid-handwriting-recognition\\data\\raw\\images\\upper_P\\upper_P_20260525_110849_168648.png",
  "canvas_width": 400,
  "canvas_height": 400,
  "strokes": [
    {
      "x": 192.845458984375,
      "y": 55.594451904296875,
      "t": 0.0,
      "pressure": 0.5,
      "pen_down": true
    },
    {
      "x": 192.845458984375,
      "y": 56.01789855957031,
      "t": 1.100000023841858,
      "pressure": 0.5,
      "pen_down": true
    },
    {
      "x": 193.2689208984375,
      "y": 61.522735595703125,
      "t": 17.200000047683716,
      "pressure": 0.5,
      "pen_down": true
    },
    {
      "x": 193.6923828125,
      "y": 81.4248046875,
      "t": 30.200000047683716,
      "pressure": 0.5,
      "pen_down": true
    },
    {
      "x": 192.4219970703125,
      "y": 111.9130859375,
      "t": 53.800000071525574,
      "pressure": 0.5,
      "pen_down": true
    },
    {
      "x": 190.728271484375,
      "y": 144.09515380859375,
      "t": 67.60000002384186,
      "pressure": 0.5,
      "pen_down": true
    },
    {
      "x": 189.88134765625,
      "y": 176.70065307617188,
      "t": 84.10000002384186,
      "pressure": 0.5,
      "pen_down": true
    },
    {
      "x": 188.6109619140625,
      "y": 210.57650756835938,
      "t": 100.90000009536743,
      "pressure": 0.5,
      "pen_down": true
    },
    {
      "x": 188.1875,
      "y": 248.26339721679688,
      "t": 117.5,
      "pressure": 0.5,
      "pen_down": true
    },
    {
      "x": 189.4578857421875,
      "y": 273.6702880859375,
      "t": 134.0,
      "pressure": 0.5,
      "pen_down": true
    },
    {
      "x": 192.845458984375,
      "y": 293.5723571777344,
      "t": 150.80000007152557,
      "pressure": 0.5,
      "pen_down": true
    },
    {
      "x": 197.50341796875,
      "y": 303.735107421875,
      "t": 167.20000004768372,
      "pressure": 0.5,
      "pen_down": true
    },
    {
      "x": 198.773681640625,
      "y": 305.42889404296875,
      "t": 179.10000002384186,
      "pressure": 0.5,
      "pen_down": true
    },
    {
      "x": 198.773681640625,
      "y": 305.42889404296875,
      "t": 179.80000007152557,
      "pressure": 0.5,
      "pen_down": false
    },
    {
      "x": 197.0799560546875,
      "y": 63.216522216796875,
      "t": 383.60000002384186,
      "pressure": 0.5,
      "pen_down": true
    },
    {
      "x": 203.0081787109375,
      "y": 58.13514709472656,
      "t": 384.3000000715256,
      "pressure": 0.5,
      "pen_down": true
    },
    {
      "x": 225.450927734375,
      "y": 46.278594970703125,
      "t": 397.8000000715256,
      "pressure": 0.5,
      "pen_down": true
    },
    {
      "x": 252.97509765625,
      "y": 41.19721984863281,
      "t": 417.3000000715256,
      "pressure": 0.5,
      "pen_down": true
    },
    {
      "x": 275.84130859375,
      "y": 43.7379150390625,
      "t": 433.90000009536743,
      "pressure": 0.5,
      "pen_down": true
    },
    {
      "x": 294.4730224609375,
      "y": 51.783416748046875,
      "t": 450.7000000476837,
      "pressure": 0.5,
      "pen_down": true
    },
    {
      "x": 301.2481689453125,
      "y": 64.06341552734375,
      "t": 467.40000009536743,
      "pressure": 0.5,
      "pen_down": true
    },
    {
      "x": 293.6260986328125,
      "y": 82.69514465332031,
      "t": 484.10000002384186,
      "pressure": 0.5,
      "pen_down": true
    },
    {
      "x": 268.21923828125,
      "y": 108.52548217773438,
      "t": 500.8000000715256,
      "pressure": 0.5,
      "pen_down": true
    },
    {
      "x": 234.3433837890625,
      "y": 131.81512451171875,
      "t": 517.3000000715256,
      "pressure": 0.5,
      "pen_down": true
    },
    {
      "x": 226.2978515625,
      "y": 136.89651489257812,
      "t": 532.4000000953674,
      "pressure": 0.5,
      "pen_down": true
    },
    {
      "x": 226.2978515625,
      "y": 136.89651489257812,
      "t": 532.9000000953674,
      "pressure": 0.5,
      "pen_down": false
    }
  ]
}