{
  "label": "r",
  "image_path": "C:\\Users\\Andrii\\Documents\\GitHub\\Hybrid-handwriting-recognition\\data\\raw\\images\\lower_r\\lower_r_20260525_111536_990379.png",
  "canvas_width": 400,
  "canvas_height": 400,
  "strokes": [
    {
      "x": 186.0703125,
      "y": 148.7530517578125,
      "t": 0.0,
      "pressure": 0.5,
      "pen_down": true
    },
    {
      "x": 184.37646484375,
      "y": 158.06890869140625,
      "t": 0.5999999046325684,
      "pressure": 0.5,
      "pen_down": true
    },
    {
      "x": 178.87158203125,
      "y": 188.13375854492188,
      "t": 12.799999952316284,
      "pressure": 0.5,
      "pen_down": true
    },
    {
      "x": 173.790283203125,
      "y": 219.89236450195312,
      "t": 34.199999928474426,
      "pressure": 0.5,
      "pen_down": true
    },
    {
      "x": 170.4027099609375,
      "y": 246.9930419921875,
      "t": 50.89999997615814,
      "pressure": 0.5,
      "pen_down": true
    },
    {
      "x": 168.7088623046875,
      "y": 263.0840759277344,
      "t": 67.69999992847443,
      "pressure": 0.5,
      "pen_down": true
    },
    {
      "x": 167.862060546875,
      "y": 273.246826171875,
      "t": 84.29999995231628,
      "pressure": 0.5,
      "pen_down": true
    },
    {
      "x": 168.7088623046875,
      "y": 274.0937194824219,
      "t": 101.89999997615814,
      "pressure": 0.5,
      "pen_down": true
    },
    {
      "x": 172.943359375,
      "y": 259.2730407714844,
      "t": 117.5,
      "pressure": 0.5,
      "pen_down": true
    },
    {
      "x": 183.9530029296875,
      "y": 220.7392578125,
      "t": 134.09999990463257,
      "pressure": 0.5,
      "pen_down": true
    },
    {
      "x": 199.62060546875,
      "y": 176.70065307617188,
      "t": 150.79999995231628,
      "pressure": 0.5,
      "pen_down": true
    },
    {
      "x": 216.98193359375,
      "y": 139.43719482421875,
      "t": 167.39999997615814,
      "pressure": 0.5,
      "pen_down": true
    },
    {
      "x": 234.3433837890625,
      "y": 114.03030395507812,
      "t": 184.19999992847443,
      "pressure": 0.5,
      "pen_down": true
    },
    {
      "x": 248.317138671875,
      "y": 100.0565185546875,
      "t": 201.09999990463257,
      "pressure": 0.5,
      "pen_down": true
    },
    {
      "x": 258.9033203125,
      "y": 95.39859008789062,
      "t": 217.59999990463257,
      "pressure": 0.5,
      "pen_down": true
    },
    {
      "x": 264.408203125,
      "y": 100.90341186523438,
      "t": 234.59999990463257,
      "pressure": 0.5,
      "pen_down": true
    },
    {
      "x": 263.9847412109375,
      "y": 127.1572265625,
      "t": 251.09999990463257,
      "pressure": 0.5,
      "pen_down": true
    },
    {
      "x": 258.47998046875,
      "y": 167.8082275390625,
      "t": 268.0,
      "pressure": 0.5,
      "pen_down": true
    },
    {
      "x": 256.7861328125,
      "y": 188.98065185546875,
      "t": 284.6999999284744,
      "pressure": 0.5,
      "pen_down": true
    },
    {
      "x": 256.7861328125,
      "y": 188.98065185546875,
      "t": 290.1999999284744,
      "pressure": 0.5,
      "pen_down": false
    }
  ]
}