{
  "label": "e",
  "image_path": "C:\\Users\\Andrii\\Documents\\GitHub\\Hybrid-handwriting-recognition\\data\\raw\\images\\lower_e\\lower_e_20260525_102734_255991.png",
  "canvas_width": 400,
  "canvas_height": 400,
  "strokes": [
    {
      "x": 131.24267578125,
      "y": 257.03857421875,
      "t": 0.0,
      "pressure": 0.5,
      "pen_down": true
    },
    {
      "x": 132.089599609375,
      "y": 257.4620056152344,
      "t": 0.8999999761581421,
      "pressure": 0.5,
      "pen_down": true
    },
    {
      "x": 139.2882080078125,
      "y": 260.849609375,
      "t": 23.700000047683716,
      "pressure": 0.5,
      "pen_down": true
    },
    {
      "x": 155.802734375,
      "y": 266.7778625488281,
      "t": 31.0,
      "pressure": 0.5,
      "pen_down": true
    },
    {
      "x": 176.128173828125,
      "y": 268.4716491699219,
      "t": 58.39999997615814,
      "pressure": 0.5,
      "pen_down": true
    },
    {
      "x": 202.805419921875,
      "y": 263.3902893066406,
      "t": 74.10000002384186,
      "pressure": 0.5,
      "pen_down": true
    },
    {
      "x": 230.32958984375,
      "y": 252.8040771484375,
      "t": 91.30000007152557,
      "pressure": 0.5,
      "pen_down": true
    },
    {
      "x": 254.466064453125,
      "y": 240.10064697265625,
      "t": 108.0,
      "pressure": 0.5,
      "pen_down": true
    },
    {
      "x": 275.6385498046875,
      "y": 225.70339965820312,
      "t": 123.80000007152557,
      "pressure": 0.5,
      "pen_down": true
    },
    {
      "x": 287.91845703125,
      "y": 211.7296142578125,
      "t": 142.39999997615814,
      "pressure": 0.5,
      "pen_down": true
    },
    {
      "x": 292.576416015625,
      "y": 199.44961547851562,
      "t": 158.10000002384186,
      "pressure": 0.5,
      "pen_down": true
    },
    {
      "x": 288.765380859375,
      "y": 187.59304809570312,
      "t": 173.80000007152557,
      "pressure": 0.5,
      "pen_down": true
    },
    {
      "x": 277.332275390625,
      "y": 173.19583129882812,
      "t": 190.70000004768372,
      "pressure": 0.5,
      "pen_down": true
    },
    {
      "x": 259.970947265625,
      "y": 163.87994384765625,
      "t": 207.89999997615814,
      "pressure": 0.5,
      "pen_down": true
    },
    {
      "x": 237.95166015625,
      "y": 165.57376098632812,
      "t": 224.10000002384186,
      "pressure": 0.5,
      "pen_down": true
    },
    {
      "x": 205.76953125,
      "y": 178.70065307617188,
      "t": 242.89999997615814,
      "pressure": 0.5,
      "pen_down": true
    },
    {
      "x": 176.5516357421875,
      "y": 205.37786865234375,
      "t": 257.60000002384186,
      "pressure": 0.5,
      "pen_down": true
    },
    {
      "x": 151.99169921875,
      "y": 243.06475830078125,
      "t": 274.3000000715256,
      "pressure": 0.5,
      "pen_down": true
    },
    {
      "x": 141.828857421875,
      "y": 273.97650146484375,
      "t": 290.7000000476837,
      "pressure": 0.5,
      "pen_down": true
    },
    {
      "x": 140.1351318359375,
      "y": 295.5723571777344,
      "t": 307.2000000476837,
      "pressure": 0.5,
      "pen_down": true
    },
    {
      "x": 150.2978515625,
      "y": 309.546142578125,
      "t": 324.10000002384186,
      "pressure": 0.5,
      "pen_down": true
    },
    {
      "x": 169.7764892578125,
      "y": 319.7088928222656,
      "t": 340.60000002384186,
      "pressure": 0.5,
      "pen_down": true
    },
    {
      "x": 191.7957763671875,
      "y": 322.67303466796875,
      "t": 357.8000000715256,
      "pressure": 0.5,
      "pen_down": true
    },
    {
      "x": 215.932373046875,
      "y": 323.09649658203125,
      "t": 370.5,
      "pressure": 0.5,
      "pen_down": true
    },
    {
      "x": 215.932373046875,
      "y": 323.09649658203125,
      "t": 371.0,
      "pressure": 0.5,
      "pen_down": false
    },
    {
      "x": 270.1336669921875,
      "y": 315.8978576660156,
      "t": 416.0,
      "pressure": 0.5,
      "pen_down": true
    },
    {
      "x": 270.1336669921875,
      "y": 315.8978576660156,
      "t": 416.5,
      "pressure": 0.5,
      "pen_down": false
    }
  ]
}